{
  "shadow": {
    "device": {
      "$type": "shadow",
      "$value": [
        {
          "color": "#0000002E",
          "offsetX": "0px",
          "offsetY": "40px",
          "blur": "80px",
          "spread": "0px"
        },
        {
          "color": "#0000001F",
          "offsetX": "0px",
          "offsetY": "0px",
          "blur": "0px",
          "spread": "1px"
        }
      ]
    },
    "cardHover": {
      "$type": "shadow",
      "$value": {
        "color": "#0000001F",
        "offsetX": "0px",
        "offsetY": "8px",
        "blur": "24px",
        "spread": "0px"
      }
    },
    "knob": {
      "$type": "shadow",
      "$value": [
        {
          "color": "#3D342A1F",
          "offsetX": "0px",
          "offsetY": "1px",
          "blur": "2px",
          "spread": "0px"
        },
        {
          "color": "#3D342A14",
          "offsetX": "0px",
          "offsetY": "2px",
          "blur": "6px",
          "spread": "0px"
        }
      ]
    },
    "moodBlob": {
      "$type": "shadow",
      "$value": {
        "color": "#C4805C61",
        "offsetX": "0px",
        "offsetY": "16px",
        "blur": "40px",
        "spread": "0px"
      }
    },
    "sliderThumb": {
      "$type": "shadow",
      "$value": [
        {
          "color": "#C8B89E70",
          "offsetX": "0px",
          "offsetY": "8px",
          "blur": "24px",
          "spread": "0px"
        },
        {
          "color": "#00000026",
          "offsetX": "0px",
          "offsetY": "2px",
          "blur": "6px",
          "spread": "0px"
        }
      ]
    }
  }
}